gemcat/__init__.py
gemcat/adjacency_transformation.py
gemcat/cli.py
gemcat/expression.py
gemcat/io.py
gemcat/model.py
gemcat/model_manager.py
gemcat/ranking.py
gemcat/utils.py
gemcat/verification.py
gemcat/workflows.py
gemcat-1.4.1.dist-info/licenses/LICENSE
gemcat-1.4.1.dist-info/METADATA
gemcat-1.4.1.dist-info/WHEEL
gemcat-1.4.1.dist-info/entry_points.txt
gemcat-1.4.1.dist-info/top_level.txt
gemcat-1.4.1.dist-info/RECORD
