Metadata-Version: 2.4
Name: gemcat
Version: 1.4.1
Summary: A toolbox for gene expression-based prediction of metabolic alterations
Author-email: Roland Sauter <roland.sauter@uit.no>
Keywords: python,bioinformatics,modeling,metabolites,omics
Requires-Python: >=3.10
License-File: LICENSE
Requires-Dist: numpy==2.1.*
Requires-Dist: pandas==2.2.*
Requires-Dist: cobra==0.29.*
Requires-Dist: networkx==3.3.*
Requires-Dist: scipy==1.14.*
Requires-Dist: sympy==1.13.*
Provides-Extra: dev
Requires-Dist: pytest==8.3.*; extra == "dev"
Requires-Dist: black==24.8.*; extra == "dev"
Requires-Dist: isort==5.13.*; extra == "dev"
Requires-Dist: pylint==3.2.*; extra == "dev"
Requires-Dist: ruff==0.6.*; extra == "dev"
Requires-Dist: requests==2.32.*; extra == "dev"
Dynamic: license-file
